[
    {
        "Story": "新购物中心昨天在东区开幕，吸引了大量顾客。购物中心内设有各种品牌的商店、餐馆和娱乐设施，为市民提供了一个理想的购物和休闲场所。",
        "QuestionsList": [
            {
                "Question": "新购物中心在哪里开幕？",
                "OptionA": "南区",
                "OptionB": "西区",
                "OptionC": "东区",
                "OptionD": "北区",
                "Answer": "OptionC"
            }
        ]
    },
    {
        "Story": "城市博物馆周一闭馆，其他时间开放。博物馆里展出了丰富的历史文物和艺术作品，吸引了众多市民和游客前来参观。",
        "QuestionsList": [
            {
                "Question": "城市博物馆哪天闭馆？",
                "OptionA": "周五",
                "OptionB": "周日",
                "OptionC": "周一",
                "OptionD": "周三",
                "Answer": "OptionC"
            }
        ]
    },
    {
        "Story": "市区新开了一条公共交通线，途经10个主要车站。新交通线的开通极大地方便了市民的出行，尤其是通勤族，他们可以更快捷地到达工作地点或返回家中。",
        "QuestionsList": [
            {
                "Question": "新开的公共交通线经过几个车站？",
                "OptionA": "10",
                "OptionB": "6",
                "OptionC": "12",
                "OptionD": "8",
                "Answer": "OptionA"
            }
        ]
    },
    {
        "Story": "昨天夏季运动会在体育馆举行，吸引了众多市民前来观看比赛。比赛项目丰富多样，包括田径、游泳、篮球等，参赛选手表现出色，赢得了观众的热烈掌声。",
        "QuestionsList": [
            {
                "Question": "夏季运动会在哪里举行？",
                "OptionA": "学校",
                "OptionB": "体育馆",
                "OptionC": "游泳池",
                "OptionD": "公园",
                "Answer": "OptionB"
            }
        ]
    },
    {
        "Story": "夜市的小吃摊位在晚上7点开始营业，常常吸引很多人。夜市的美食种类繁多，价格实惠，是市民晚间休闲的好去处。",
        "QuestionsList": [
            {
                "Question": "夜市小吃摊位在晚上几点开始营业？",
                "OptionA": "9",
                "OptionB": "6",
                "OptionC": "7",
                "OptionD": "8",
                "Answer": "OptionC"
            }
        ]
    },
    {
        "Story": "电影院本周末上映一部热门动作片，影评好评如潮。许多影迷专程前来观看，电影院几乎场场爆满。",
        "QuestionsList": [
            {
                "Question": "电影院本周末上映了什么类型的电影？",
                "OptionA": "喜剧片",
                "OptionB": "剧情片",
                "OptionC": "动作片",
                "OptionD": "爱情片",
                "Answer": "OptionC"
            }
        ]
    },
    {
        "Story": "地铁车站正在进行改造工程，预计下个月完成。改造后，车站将更加现代化，提供更加便利的服务。",
        "QuestionsList": [
            {
                "Question": "地铁车站的改造工程预计何时完成？",
                "OptionA": "今年底",
                "OptionB": "下个月",
                "OptionC": "明年初",
                "OptionD": "本月",
                "Answer": "OptionB"
            }
        ]
    },
    {
        "Story": "图书馆刚刚上架了一本畅销书，作者是知名作家李明。这本书自上架以来，受到了读者的热烈欢迎，借阅量一直居高不下。",
        "QuestionsList": [
            {
                "Question": "图书馆新上的畅销书的作者是谁？",
                "OptionA": "李明",
                "OptionB": "张伟",
                "OptionC": "刘洋",
                "OptionD": "王强",
                "Answer": "OptionA"
            }
        ]
    },
    {
        "Story": "书店今天开始了全场5折的促销活动，为期一周。此次促销活动吸引了大量的书迷，他们纷纷前来购买心仪的书籍。",
        "QuestionsList": [
            {
                "Question": "书店的促销活动持续多久？",
                "OptionA": "三天",
                "OptionB": "一周",
                "OptionC": "一个月",
                "OptionD": "两周",
                "Answer": "OptionB"
            }
        ]
    },
    {
        "Story": "公园里的草坪昨天刚刚修剪过，看起来特别整洁。修剪后的草坪不仅美观，而且为前来休闲的市民提供了更舒适的环境。",
        "QuestionsList": [
            {
                "Question": "公园草坪是什么时候修剪的？",
                "OptionA": "上周",
                "OptionB": "今年春天",
                "OptionC": "本月初",
                "OptionD": "昨天",
                "Answer": "OptionD"
            }
        ]
    }
]